colassigner/__init__.py
colassigner/constants.py
colassigner/core.py
colassigner/dag_from_ast.py
colassigner/experiment.py
colassigner/meta_base.py
colassigner/type_hinting.py
colassigner/util.py
colassigner/tests/__init__.py
colassigner/tests/test_accessor.py
colassigner/tests/test_annotations.py
colassigner/tests/test_assigner.py
colassigner/tests/test_dag.py
colassigner/tests/test_experiment.py
colassigner/tests/test_type_retention.py
colassigner/tests/test_util.py
colassigner-0.4.2.dist-info/LICENSE
colassigner-0.4.2.dist-info/WHEEL
colassigner-0.4.2.dist-info/METADATA
colassigner-0.4.2.dist-info/RECORD
