Metadata-Version: 2.1
Name: colassigner
Version: 0.4.2
Summary: Helper for assigning and accessing pandas columns
Author-email: Endre Márk Borza <endremborza@gmail.com>
Requires-Python: >=3.10
Requires-Dist: pandas
Requires-Dist: branthebuilder[doc] ; extra == "doc"
Requires-Dist: branthebuilder ; extra == "test"
Project-URL: Homepage, https://github.com/endremborza/colassigner
Provides-Extra: doc
Provides-Extra: test
